oneiron/__init__.py
oneiron-0.0.3.dist-info/METADATA
oneiron-0.0.3.dist-info/WHEEL
oneiron-0.0.3.dist-info/RECORD
