Metadata-Version: 2.4
Name: oneiron
Version: 0.0.3
Summary: Memory engine (coming soon)
Author: Oneiron Team
License-Expression: AGPL-3.0-or-later
Classifier: Development Status :: 1 - Planning
Classifier: License :: OSI Approved :: GNU Affero General Public License v3 or later (AGPLv3+)
Classifier: Programming Language :: Python :: 3
Requires-Python: >=3.10
